{"facturas":[{"legacyId":"df6b40c2-29dc-46b2-b6f9-c6e8e2491fa3","condominioId":"j57539w0yhh0bzvc6r7xmmg67s8avkrw","unidadId":"jd7899gp11at89x4ndymav3qc58av6sn","membershipId":"j978zenmf33k1s6hdggvx81q2x8atds6","numeroFactura":"FAC-2026-06-0161","numeroInterno":"10681","periodo":"2026-06","periodoLabel":"Junio / 2026","residenteNombre":"JIMENEZ GIL GERARDO","apto":"809 M8","vrAdmon":314000,"lineas":[{"codigo":1,"concepto":"CUOTA DE ADMINISTRACIÓN","saldoAnterior":314000,"actual":314000,"total":628000},{"codigo":5,"concepto":"CONT. VOL. AREAS COMUNES","saldoAnterior":161000,"actual":182000,"total":343000},{"codigo":8,"concepto":"POZO PTTM Y CORMACARENA","saldoAnterior":21000,"actual":21000,"total":42000},{"codigo":9,"concepto":"RETROACTIVO","saldoAnterior":25000,"actual":25000,"total":50000}],"saldoAFavor":0,"totalAPagar":1063000,"fechaEmision":0,"fechaVencimiento":0,"estado":"pendiente","pdfUrl":"https://vekino.s3.us-east-1.amazonaws.com/condominios/facturas/1a56ac61-2332-46f2-881c-a38acf516fde/2026-06/unidad-809.pdf"},{"legacyId":"20fcb1f4-297d-4d71-a5b5-6ca15fe03bcb","condominioId":"j57539w0yhh0bzvc6r7xmmg67s8avkrw","unidadId":"jd714aejjrj8h5chxtnxzfg0y58atyp5","membershipId":"j974d2yyy0nhczfd2g6r45mcy98atqj0","numeroFactura":"FAC-2026-06-0162","numeroInterno":"11195","periodo":"2026-06","periodoLabel":"Junio / 2026","residenteNombre":"BELTRAN MARTHA","apto":"811 M8","vrAdmon":314000,"lineas":[{"codigo":1,"concepto":"CUOTA DE ADMINISTRACIÓN","saldoAnterior":0,"actual":314000,"total":314000},{"codigo":8,"concepto":"POZO PTTM Y CORMACARENA","saldoAnterior":0,"actual":21000,"total":21000},{"codigo":9,"concepto":"RETROACTIVO","saldoAnterior":0,"actual":25000,"total":25000}],"saldoAFavor":0,"totalAPagar":360000,"fechaEmision":0,"fechaVencimiento":0,"estado":"pendiente","pdfUrl":"https://vekino.s3.us-east-1.amazonaws.com/condominios/facturas/1a56ac61-2332-46f2-881c-a38acf516fde/2026-06/unidad-811.pdf"},{"legacyId":"f858f91d-9338-4041-ab2b-bf2c7f2ad853","condominioId":"j57539w0yhh0bzvc6r7xmmg67s8avkrw","unidadId":"jd7cj7tc6p9rdzdqfdzvm67rvn8avdcy","numeroFactura":"FAC-2026-06-0163","numeroInterno":"11196","periodo":"2026-06","periodoLabel":"Junio / 2026","residenteNombre":"PERSON FLORIDO D. / LEIDY JOHANA QUINTER","apto":"812 M8","vrAdmon":314000,"lineas":[{"codigo":1,"concepto":"CUOTA DE ADMINISTRACIÓN","saldoAnterior":0,"actual":314000,"total":314000},{"codigo":8,"concepto":"POZO PTTM Y CORMACARENA","saldoAnterior":0,"actual":21000,"total":21000},{"codigo":9,"concepto":"RETROACTIVO","saldoAnterior":0,"actual":25000,"total":25000}],"saldoAFavor":0,"totalAPagar":360000,"fechaEmision":0,"fechaVencimiento":0,"estado":"pendiente","pdfUrl":"https://vekino.s3.us-east-1.amazonaws.com/condominios/facturas/1a56ac61-2332-46f2-881c-a38acf516fde/2026-06/unidad-812.pdf"},{"legacyId":"29929e6c-d96a-4a0e-b5ae-27b59e4ed6ca","condominioId":"j57539w0yhh0bzvc6r7xmmg67s8avkrw","unidadId":"jd7evw2kvamt63pk09jxghhjjx8atrzz","numeroFactura":"FAC-2026-06-0164","numeroInterno":"0","periodo":"2026-06","periodoLabel":"","residenteNombre":"Residente","vrAdmon":0,"lineas":[],"saldoAFavor":0,"totalAPagar":24800120,"fechaEmision":0,"fechaVencimiento":0,"estado":"pendiente","pdfUrl":"https://vekino.s3.us-east-1.amazonaws.com/condominios/facturas/1a56ac61-2332-46f2-881c-a38acf516fde/2026-06/unidad-813.pdf"},{"legacyId":"ff1f8533-ac51-45bf-83ea-47d138734603","condominioId":"j57539w0yhh0bzvc6r7xmmg67s8avkrw","unidadId":"jd76038kdhjf6capcbkxjc72fn8atpch","membershipId":"j9704k75keyq5391j4ztmm69j58avb69","numeroFactura":"FAC-2026-06-0165","numeroInterno":"11198","periodo":"2026-06","periodoLabel":"Junio / 2026","residenteNombre":"ROJAS CUERVO MARIA CAMILA","apto":"814 M8","vrAdmon":314000,"lineas":[{"codigo":1,"concepto":"CUOTA DE ADMINISTRACIÓN","saldoAnterior":0,"actual":314000,"total":314000},{"codigo":5,"concepto":"CONT. VOL. AREAS COMUNES","saldoAnterior":0,"actual":199000,"total":199000},{"codigo":8,"concepto":"POZO PTTM Y CORMACARENA","saldoAnterior":0,"actual":21000,"total":21000},{"codigo":9,"concepto":"RETROACTIVO","saldoAnterior":0,"actual":25000,"total":25000}],"saldoAFavor":0,"totalAPagar":559000,"fechaEmision":0,"fechaVencimiento":0,"estado":"pendiente","pdfUrl":"https://vekino.s3.us-east-1.amazonaws.com/condominios/facturas/1a56ac61-2332-46f2-881c-a38acf516fde/2026-06/unidad-814.pdf"},{"legacyId":"3fca2ed1-c57d-4a7a-8d0d-3f2c353736c3","condominioId":"j57539w0yhh0bzvc6r7xmmg67s8avkrw","unidadId":"jd76d4a7535zkp7bhtgb78rwx98atnf3","membershipId":"j976zzhtz066detsekdyq0xgrn8atd3k","numeroFactura":"FAC-2026-06-0166","numeroInterno":"10994","periodo":"2026-06","periodoLabel":"Junio / 2026","residenteNombre":"BAICUE NAVARRO JOSE VIRGILIO","apto":"815 M8","vrAdmon":314000,"lineas":[{"codigo":1,"concepto":"CUOTA DE ADMINISTRACIÓN","saldoAnterior":0,"actual":314000,"total":314000},{"codigo":8,"concepto":"POZO PTTM Y CORMACARENA","saldoAnterior":0,"actual":21000,"total":21000},{"codigo":9,"concepto":"RETROACTIVO","saldoAnterior":6650,"actual":25000,"total":31650}],"saldoAFavor":0,"totalAPagar":366650,"fechaEmision":0,"fechaVencimiento":0,"estado":"pendiente","pdfUrl":"https://vekino.s3.us-east-1.amazonaws.com/condominios/facturas/1a56ac61-2332-46f2-881c-a38acf516fde/2026-06/unidad-815.pdf"},{"legacyId":"8b0a3598-d020-4c47-a232-9cd42ce46c4c","condominioId":"j57539w0yhh0bzvc6r7xmmg67s8avkrw","unidadId":"jd766t3rhw7jspmjn2a7c0f80d8avxf8","numeroFactura":"FAC-2026-06-0167","numeroInterno":"11200","periodo":"2026-06","periodoLabel":"Junio / 2026","residenteNombre":"BAICUE NAVARRO JOSE VIRGILIO","apto":"816 M8","vrAdmon":314000,"lineas":[{"codigo":1,"concepto":"CUOTA DE ADMINISTRACIÓN","saldoAnterior":0,"actual":314000,"total":314000},{"codigo":8,"concepto":"POZO PTTM Y CORMACARENA","saldoAnterior":0,"actual":21000,"total":21000},{"codigo":9,"concepto":"RETROACTIVO","saldoAnterior":0,"actual":25000,"total":25000}],"saldoAFavor":0,"totalAPagar":360000,"fechaEmision":0,"fechaVencimiento":0,"estado":"pendiente","pdfUrl":"https://vekino.s3.us-east-1.amazonaws.com/condominios/facturas/1a56ac61-2332-46f2-881c-a38acf516fde/2026-06/unidad-816.pdf"},{"legacyId":"ef7836b7-21e8-4a04-9291-e47978f84de5","condominioId":"j57539w0yhh0bzvc6r7xmmg67s8avkrw","unidadId":"jd70rx42x86jbvz64n32xwnkch8atwyj","membershipId":"j97c9x85jfsb6gsjdt9rakeav98avfta","numeroFactura":"FAC-2026-06-0168","numeroInterno":"11201","periodo":"2026-06","periodoLabel":"Junio / 2026","residenteNombre":"PEREZ HERNANDEZ YURY","apto":"817 M8","vrAdmon":314000,"lineas":[{"codigo":1,"concepto":"CUOTA DE ADMINISTRACIÓN","saldoAnterior":0,"actual":314000,"total":314000},{"codigo":8,"concepto":"POZO PTTM Y CORMACARENA","saldoAnterior":0,"actual":21000,"total":21000},{"codigo":9,"concepto":"RETROACTIVO","saldoAnterior":0,"actual":25000,"total":25000}],"saldoAFavor":0,"totalAPagar":360000,"fechaEmision":0,"fechaVencimiento":0,"estado":"pendiente","pdfUrl":"https://vekino.s3.us-east-1.amazonaws.com/condominios/facturas/1a56ac61-2332-46f2-881c-a38acf516fde/2026-06/unidad-817.pdf"},{"legacyId":"51a30a30-5e22-4572-93ae-396721220a0d","condominioId":"j57539w0yhh0bzvc6r7xmmg67s8avkrw","unidadId":"jd72f75qpketsvqgfjqaryf9b18at0xt","membershipId":"j971m9c1s3gpzraqga6ynp38zx8at996","numeroFactura":"FAC-2026-06-0169","numeroInterno":"11202","periodo":"2026-06","periodoLabel":"Junio / 2026","residenteNombre":"CARANTON HERNANDEZ DEYANIRA","apto":"818 M8","vrAdmon":314000,"lineas":[{"codigo":1,"concepto":"CUOTA DE ADMINISTRACIÓN","saldoAnterior":0,"actual":314000,"total":314000},{"codigo":8,"concepto":"POZO PTTM Y CORMACARENA","saldoAnterior":0,"actual":21000,"total":21000},{"codigo":9,"concepto":"RETROACTIVO","saldoAnterior":0,"actual":25000,"total":25000}],"saldoAFavor":0,"totalAPagar":360000,"fechaEmision":0,"fechaVencimiento":0,"estado":"pendiente","pdfUrl":"https://vekino.s3.us-east-1.amazonaws.com/condominios/facturas/1a56ac61-2332-46f2-881c-a38acf516fde/2026-06/unidad-818.pdf"},{"legacyId":"a29ef7b6-d14b-4467-b30e-1a84966eb11e","condominioId":"j57539w0yhh0bzvc6r7xmmg67s8avkrw","unidadId":"jd75beza114by5p6regq981a4s8av2s2","membershipId":"j978wn920j1fthjty9xebgrs7x8atwdv","numeroFactura":"FAC-2026-06-0170","numeroInterno":"11203","periodo":"2026-06","periodoLabel":"Junio / 2026","residenteNombre":"CAMILO ANDRES CARRILLO","apto":"819 M8","vrAdmon":314000,"lineas":[{"codigo":1,"concepto":"CUOTA DE ADMINISTRACIÓN","saldoAnterior":0,"actual":314000,"total":314000},{"codigo":5,"concepto":"CONT. VOL. AREAS COMUNES","saldoAnterior":0,"actual":63000,"total":63000},{"codigo":8,"concepto":"POZO PTTM Y CORMACARENA","saldoAnterior":0,"actual":21000,"total":21000},{"codigo":9,"concepto":"RETROACTIVO","saldoAnterior":0,"actual":25000,"total":25000}],"saldoAFavor":0,"totalAPagar":423000,"fechaEmision":0,"fechaVencimiento":0,"estado":"pendiente","pdfUrl":"https://vekino.s3.us-east-1.amazonaws.com/condominios/facturas/1a56ac61-2332-46f2-881c-a38acf516fde/2026-06/unidad-819.pdf"}]}